{
    "nodes": {
        "button": {
            "type": "button",
            "x": 100,
            "y": 100
        },
        "switch": {
            "type": "switch",
            "x": 350,
            "y": 100
        },
        "led": {
            "type": "led",
            "x": 600,
            "y": 100,
            "inputs": {
                "brightness": {
                    "value": 80,
                    "unit": "%"
                }
            }
        }
    },

    "links": [{
        "fromNode": "button",
        "fromOutput": "press",
        "toNode": "switch",
        "toInput": "toggle"
    }, {
        "fromNode": "switch",
        "fromOutput": "output",
        "toNode": "led",
        "toInput": "enabled"
    }]
}
